1081_HW1/autoseller7.v
module autoseller(clk, reset, enable_i, money_i, drinktype_i, ready_o, enable_o, change_o, drink_o);

input clk,reset,enable_i;
input [5:0] money_i; 
input [1:0] drinktype_i; 

output reg ready_o;
output reg enable_o;
output reg [5:0] change_o;
output reg [1:0] drink_o;

wire [5:0] drinkcost [0:3];
assign {drinkcost[0],drinkcost[1],drinkcost[2],drinkcost[3]}  = {6'd0,6'd30,6'd20,6'd15};
// parameter [23:0] drinkcost  = {6'd15,6'd20,6'd30,6'd0};
wire [5:0] cost;
assign cost = (enable_i)?drinkcost[drinktype_i]:6'd0;

// sequential
always @(posedge clk or posedge reset) begin
    if (reset) begin
        ready_o <= 1'b1;
    end 
    else begin
        if(enable_i) begin
        if(money_i<cost)begin
            change_o <= money_i;
            drink_o <= 2'b00;
        end
        else begin
            change_o <= money_i-cost;
            drink_o <= drinktype_i;
        end
            // change_o <= (money_i<drinkcost[6*drinktype_i+:6])?money_i:(money_i-drinkcost[6*drinktype_i+:6]);
            // drink_o <= (money_i<drinkcost[6*drinktype_i+:6])?2'b00:drinktype_i;
            enable_o <= 1'b1;
            ready_o <= 1'b1;
        end
        else begin
            enable_o <= 1'b0;
            ready_o <= 1'b1;
        end
    end
end

endmodule

1081_HW1/testbench1.v
`timescale 1ns/10ps

`define CYCLE 10
// modify if need
`define ENDCYCLE  400

`define PATTERN_MONEY  "pattern1_money.dat"
`define PATTERN_TYPE   "pattern1_type.dat"
`define NUM_PATTERN 1
`define NUM_OUT     1
`define GOLDEN_CHANGE  "golden1_change.dat"
`define GOLDEN_TYPE    "golden1_type.dat"

// color definition
`define YEL "%c[0;33m",27
`define BLK "%c[0;m",27



module testbench();

  


  reg         clk, reset, enable_i;
  reg   [5:0] money_i;
  reg   [1:0] drinktype_i;
  
  wire        ready_o, enable_o;
  wire  [5:0] change_o;
  wire  [1:0] drink_o;  
 
  reg [3:0] cnt;
  reg [3:0] cnt_pattern;
  integer pat;
  integer gold;
  integer err;
  
  reg [5:0] pattern_money [0:15];
  reg [1:0] pattern_type [0:15];
  reg [5:0] golden_change  [0:15];
  reg [1:0] golden_type [0:15];


  autoseller DUT(
    .clk(clk),
	.reset(reset), 
	.enable_i(enable_i), 
	.money_i(money_i), 
	.drinktype_i(drinktype_i), 
	.ready_o(ready_o), 
	.enable_o(enable_o), 
	.change_o(change_o), 
	.drink_o(drink_o)
  );

  
// -------------------------------------------------------- //
//   Global behavior
// -------------------------------------------------------- //



always #(`CYCLE/2) clk = ~clk;

initial begin
  `ifdef FSDB
    $fsdbDumpfile("autoseller.fsdb");
	$fsdbDumpvars();
  `endif

  // `ifdef VCD
    $dumpfile("autoseller.vcd");
	$dumpvars();
  // `endif
end

//
initial begin
  $readmemh(`PATTERN_MONEY, pattern_money);
  $readmemb(`PATTERN_TYPE, pattern_type);
  $readmemh(`GOLDEN_CHANGE, golden_change);
  $readmemb(`GOLDEN_TYPE, golden_type);
  $display("\n ================ 2014 Spring ICD HW4 - Automatic Selling Machine ================= ");
              
  pat=0;
  gold=0;
  err=0;
  clk =1;
  reset =0; 
  enable_i=0;
  money_i =0;
  drinktype_i=0;
  
  cnt=`NUM_OUT;
  cnt_pattern=`NUM_PATTERN;  
  
  //reset
  #(`CYCLE +3) reset = 1;
  #(`CYCLE/2) reset = 0;
end

// input value
always@(negedge clk)
begin
  #1
  if(ready_o===1 && pat<cnt_pattern) begin
    //$display("\n =========================================================================");
    //$display("                         Input Pattern number%2d, %2d",pat+1, pattern[pat]);
    //$display(" =========================================================================");
  	
    enable_i = 1'b1;
    money_i = pattern_money[pat];
	drinktype_i = pattern_type[pat];
	pat = pat+1;
  end 
  else begin
    enable_i = 1'b0;
    money_i = 6'b0;
	drinktype_i = 2'b0;
  end 
end

// Finish
initial begin
  #(`CYCLE*`ENDCYCLE);
  #1;
  if(cnt>0) begin
    $display(" =================== TIME OUT ======================\n");
    $display("         There are someting wrong in your code...  \n");
    $display("           If you need more simulation time         ");
    $display("  You can try to modify ENDCYCLE in the testbench .\n");
    $display(" =================== TIME OUT ======================\n");
  end
  $finish;
end

always@(negedge clk)
begin
  if(cnt==0) begin
    if(err==0) begin
        $display("\n");
        $display("                      ****************************              ");
        $display("                      **                        **        /|__/|");
        $display("                      **  Congratulations !!    **      / O,O  |");
        $display("                      **                        **    /_____   |");
        $display("                      **  You pass this test!!  **   /^ ^ ^ \\  |");
        $display("                      **                        **  |^ ^ ^ ^ |w|");
        $display("                      ****************************   \\m___m__|_|");
        $display("\n");
        $finish;
    end
    else begin
        $display("\n");
        $display("                      ****************************              ");
        $display("                      **      *       *         **        /|__/|");
        $display("                      **        *   *           **      / >,<  |");
        $display("                      **          *             **    /_____   |");
        $display("                      **        *   *           **   /^ ^ ^ \\  |");
        $display("                      **      *       *         **  |^ ^ ^ ^ |w|");
        $display("                      ****************************   \\m___m__|_|");
        $display("\n");
        $display("There are %d errors in your results\n", err);
        $finish;      
    end
  end
  else begin
    if(enable_o===1)
    begin
      cnt = cnt-1;
      if(change_o!==golden_change[gold] || drink_o!==golden_type[gold])
      begin
        //$display("  At %5d NS",$time,`YEL," Error!",`BLK,"   The out_num should be: %3d", golden_num[gold], " Your: %3d", out_num);
        $display("  At %5d NS",$time,`YEL," Error!",`BLK,"   The change, type should be: %3d, %2b", golden_change[gold], golden_type[gold], " Your: %3d, %2b", change_o, drink_o);
		err =err+1;
        gold = gold+1;
      end
      else begin
        //$display("  At %5d NS",$time," Correct! The out_num should be: %3d", golden_num[gold], " Your: %3d", out_num);
		$display("  At %5d NS",$time," Correct! The change, type should be: %3d, %2b", golden_change[gold], golden_type[gold], " Your: %3d, %2b", change_o, drink_o);
        gold = gold+1;
      end
    end
  end
end

endmodule

1081_HW1/out.vcd
$date
	Sun Sep 29 18:24:34 2019
$end
$version
	Icarus Verilog
$end
$timescale
	10ps
$end
$scope module testbench $end
$var wire 1 ! ready_o $end
$var wire 1 " enable_o $end
$var wire 2 # drink_o [1:0] $end
$var wire 6 $ change_o [5:0] $end
$var reg 1 % clk $end
$var reg 4 & cnt [3:0] $end
$var reg 4 ' cnt_pattern [3:0] $end
$var reg 2 ( drinktype_i [1:0] $end
$var reg 1 ) enable_i $end
$var reg 6 * money_i [5:0] $end
$var reg 1 + reset $end
$var integer 32 , err [31:0] $end
$var integer 32 - gold [31:0] $end
$var integer 32 . pat [31:0] $end
$scope module DUT $end
$var wire 1 % clk $end
$var wire 2 / drinktype_i [1:0] $end
$var wire 1 ) enable_i $end
$var wire 6 0 money_i [5:0] $end
$var wire 1 + reset $end
$var wire 6 1 cost [5:0] $end
$var reg 6 2 change_o [5:0] $end
$var reg 2 3 drink_o [1:0] $end
$var reg 1 " enable_o $end
$var reg 1 ! ready_o $end
$upscope $end
$upscope $end
$enddefinitions $end
#0
$dumpvars
bx 3
bx 2
b0 1
b0 0
b0 /
b0 .
b0 -
b0 ,
0+
b0 *
0)
b0 (
b1010 '
b1010 &
1%
bx $
bx #
0"
1!
$end
#500
0%
#600
b11110 1
b1 .
b1 (
b1 /
b101010 *
b101010 0
1)
#1000
1"
b1 #
b1 3
b1100 $
b1100 2
1%
#1300
1+
#1500
b1 -
b1001 &
0%
#1600
b10100 1
b10 .
b10 (
b10 /
b10101 *
b10101 0
#1800
0+
#2000
b10 #
b10 3
b1 $
b1 2
1%
#2500
b10 -
b1000 &
0%
#2600
b1111 1
b11 .
b11 (
b11 /
b110 *
b110 0
#3000
b0 #
b0 3
b110 $
b110 2
1%
#3500
b11 -
b111 &
0%
#3600
b10100 1
b100 .
b10 (
b10 /
b100001 *
b100001 0
#4000
b10 #
b10 3
b1101 $
b1101 2
1%
#4500
b100 -
b110 &
0%
#4600
b0 1
b101 .
b0 (
b0 /
b10110 *
b10110 0
#5000
b0 #
b0 3
b10110 $
b10110 2
1%
#5500
b101 -
b101 &
0%
#5600
b11110 1
b110 .
b1 (
b1 /
b11110 *
b11110 0
#6000
b1 #
b1 3
b0 $
b0 2
1%
#6500
b110 -
b100 &
0%
#6600
b0 1
b111 .
b0 (
b0 /
b1000 *
b1000 0
#7000
b0 #
b0 3
b1000 $
b1000 2
1%
#7500
b111 -
b11 &
0%
#7600
b10100 1
b1000 .
b10 (
b10 /
b11011 *
b11011 0
#8000
b10 #
b10 3
b111 $
b111 2
1%
#8500
b1000 -
b10 &
0%
#8600
b1111 1
b1001 .
b11 (
b11 /
b10010 *
b10010 0
#9000
b11 #
b11 3
b11 $
b11 2
1%
#9500
b1001 -
b1 &
0%
#9600
b10100 1
b1010 .
b10 (
b10 /
b100 *
b100 0
#10000
b0 #
b0 3
b100 $
b100 2
1%
#10500
b1010 -
b0 &
0%
#10600
b0 1
b0 (
b0 /
b0 *
b0 0
0)
#11000
0"
1%
